MysqlJiaochengCYuyanZhongwenwang/README.md
MysqlJiaochengCYuyanZhongwenwang/__init__.py
MysqlJiaochengCYuyanZhongwenwang/__main__.py
MysqlJiaochengCYuyanZhongwenwang/file.epub
MysqlJiaochengCYuyanZhongwenwang/index.html
MysqlJiaochengCYuyanZhongwenwang/css/__init__.py
MysqlJiaochengCYuyanZhongwenwang/css/annotations.css
MysqlJiaochengCYuyanZhongwenwang/css/main.css
MysqlJiaochengCYuyanZhongwenwang/css/normalize.css
MysqlJiaochengCYuyanZhongwenwang/css/popup.css
MysqlJiaochengCYuyanZhongwenwang/font/__init__.py
MysqlJiaochengCYuyanZhongwenwang/font/fontello.eot
MysqlJiaochengCYuyanZhongwenwang/font/fontello.svg
MysqlJiaochengCYuyanZhongwenwang/font/fontello.ttf
MysqlJiaochengCYuyanZhongwenwang/font/fontello.woff
MysqlJiaochengCYuyanZhongwenwang/img/__init__.py
MysqlJiaochengCYuyanZhongwenwang/img/annotator-glyph-sprite.png
MysqlJiaochengCYuyanZhongwenwang/img/annotator-icon-sprite.png
MysqlJiaochengCYuyanZhongwenwang/img/apple-touch-icon.png
MysqlJiaochengCYuyanZhongwenwang/img/cancelfullscreen.png
MysqlJiaochengCYuyanZhongwenwang/img/close.png
MysqlJiaochengCYuyanZhongwenwang/img/fullscreen.png
MysqlJiaochengCYuyanZhongwenwang/img/loader.gif
MysqlJiaochengCYuyanZhongwenwang/img/menu-icon.png
MysqlJiaochengCYuyanZhongwenwang/img/save.png
MysqlJiaochengCYuyanZhongwenwang/img/saved.png
MysqlJiaochengCYuyanZhongwenwang/img/settings-s.png
MysqlJiaochengCYuyanZhongwenwang/img/settings.png
MysqlJiaochengCYuyanZhongwenwang/img/star.png
MysqlJiaochengCYuyanZhongwenwang/js/__init__.py
MysqlJiaochengCYuyanZhongwenwang/js/epub.js
MysqlJiaochengCYuyanZhongwenwang/js/epub.min.js
MysqlJiaochengCYuyanZhongwenwang/js/epub.min.map
MysqlJiaochengCYuyanZhongwenwang/js/hooks.min.js
MysqlJiaochengCYuyanZhongwenwang/js/hooks.min.map
MysqlJiaochengCYuyanZhongwenwang/js/reader.js
MysqlJiaochengCYuyanZhongwenwang/js/reader.js.map
MysqlJiaochengCYuyanZhongwenwang/js/reader.min.js
MysqlJiaochengCYuyanZhongwenwang/js/reader.min.map
MysqlJiaochengCYuyanZhongwenwang/js/hooks/__init__.py
mysql_jiaocheng_c_yuyan_zhongwenwang-2024.3.2.0.dist-info/METADATA
mysql_jiaocheng_c_yuyan_zhongwenwang-2024.3.2.0.dist-info/WHEEL
mysql_jiaocheng_c_yuyan_zhongwenwang-2024.3.2.0.dist-info/entry_points.txt
mysql_jiaocheng_c_yuyan_zhongwenwang-2024.3.2.0.dist-info/top_level.txt
mysql_jiaocheng_c_yuyan_zhongwenwang-2024.3.2.0.dist-info/RECORD
